MrHubGui/EditForm.py
MrHubGui/GitTools.py
MrHubGui/__init__.py
MrHubGui/edit_form_ui.py
MrHubGui/github_credentials_ui.py
mr_hub_gui-0.0.2.dist-info/LICENSE
mr_hub_gui-0.0.2.dist-info/METADATA
mr_hub_gui-0.0.2.dist-info/WHEEL
mr_hub_gui-0.0.2.dist-info/entry_points.txt
mr_hub_gui-0.0.2.dist-info/top_level.txt
mr_hub_gui-0.0.2.dist-info/RECORD
