Metadata-Version: 2.1
Name: mr-hub-gui
Version: 0.0.2
Summary: A GUI to add packages to MR-Hub
Home-page: https://github.com/fsantini/mr-hub-gui
Author: Francesco Santini
Author-email: francesco.santini@unibas.ch
License: UNKNOWN
Project-URL: Bug Tracker, https://github.com/fsantini/mr-hub-gui/issues
Platform: UNKNOWN
Classifier: Programming Language :: Python :: 3
Classifier: License :: OSI Approved :: MIT License
Classifier: Operating System :: OS Independent
Requires-Python: >=3.6
Requires-Dist: requests
Requires-Dist: PySide2
Requires-Dist: PyGithub
